README.md
setup.cfg
setup.py
vacuubrand/__init__.py
vacuubrand/simulator.py
vacuubrand.egg-info/PKG-INFO
vacuubrand.egg-info/SOURCES.txt
vacuubrand.egg-info/dependency_links.txt
vacuubrand.egg-info/entry_points.txt
vacuubrand.egg-info/requires.txt
vacuubrand.egg-info/top_level.txt
vacuubrand/dcp3000/__init__.py
vacuubrand/dcp3000/dcp3000.py
vacuubrand/dcp3000/protocol.py
vacuubrand/tango/__init__.py
vacuubrand/tango/server/__init__.py
vacuubrand/tango/server/dcp3000.py