Metadata-Version: 2.1
Name: vacuubrand
Version: 2.0.0
Summary: vacuubrand library
Home-page: https://github.com/tiagocoutinho/vacuubrand
Author: Tiago Coutinho
Author-email: tcoutinho@cells.es
License: LGPLv3
Project-URL: Documentation, https://github.com/tiagocoutinho/vacuubrand
Project-URL: Source, https://github.com/tiagocoutinho/vacuubrand
Keywords: vacuubrand,library,tango
Platform: UNKNOWN
Classifier: Development Status :: 2 - Pre-Alpha
Classifier: Intended Audience :: Developers
Classifier: Natural Language :: English
Classifier: Programming Language :: Python :: 3
Classifier: Programming Language :: Python :: 3.5
Classifier: Programming Language :: Python :: 3.6
Classifier: Programming Language :: Python :: 3.7
Classifier: Programming Language :: Python :: 3.8
Provides-Extra: tango
Provides-Extra: simulator
